<annotation>
	<folder>Anh_Test</folder>
	<filename>A2441.jpeg</filename>
	<path>D:\Project1\Data\Anh_Test\A2441.jpeg</path>
	<source>
		<database>Unknown</database>
	</source>
	<size>
		<width>1280</width>
		<height>847</height>
		<depth>3</depth>
	</size>
	<segmented>0</segmented>
	<object>
		<name>number_plate</name>
		<pose>Unspecified</pose>
		<truncated>0</truncated>
		<difficult>0</difficult>
		<bndbox>
			<xmin>357</xmin>
			<ymin>288</ymin>
			<xmax>1044</xmax>
			<ymax>555</ymax>
		</bndbox>
	</object>
</annotation>
