<annotation>
	<folder>Train_1</folder>
	<filename>A95.jpg</filename>
	<path>D:\Project1\Data\Train\Train_1\A95.jpg</path>
	<source>
		<database>Unknown</database>
	</source>
	<size>
		<width>362</width>
		<height>272</height>
		<depth>3</depth>
	</size>
	<segmented>0</segmented>
	<object>
		<name>number</name>
		<pose>Unspecified</pose>
		<truncated>0</truncated>
		<difficult>0</difficult>
		<bndbox>
			<xmin>166</xmin>
			<ymin>220</ymin>
			<xmax>259</xmax>
			<ymax>244</ymax>
		</bndbox>
	</object>
</annotation>
